flashcommit/__init__.py
flashcommit/client/__init__.py
flashcommit/client/queryclient.py
flashcommit/client/reviewclient.py
flashcommit/client/reviewclientV3.py
flashcommit/console-ui.tcss
flashcommit/flash_commit_adapter.py
flashcommit/gitclient.py
flashcommit/logging.yaml
flashcommit/main.py
flashcommit/prompt_generator.py
flashcommit/ui.py
flashcommit/version.py
flashcommit-0.2.11.dist-info/METADATA
flashcommit-0.2.11.dist-info/WHEEL
flashcommit-0.2.11.dist-info/entry_points.txt
flashcommit-0.2.11.dist-info/RECORD
